cloudcoil/_context.py
cloudcoil/_pydantic.py
cloudcoil/apimachinery.py
cloudcoil/errors.py
cloudcoil/mypy.py
cloudcoil/py.typed
cloudcoil/pydantic.py
cloudcoil/resources.py
cloudcoil/version.py
cloudcoil/_testing/__init__.py
cloudcoil/_testing/clusters.py
cloudcoil/_testing/plugin.py
cloudcoil/client/__init__.py
cloudcoil/client/_api_client.py
cloudcoil/client/_config.py
cloudcoil/codegen/__init__.py
cloudcoil/codegen/generator.py
cloudcoil/codegen/import_rewriter.py
cloudcoil/codegen/ruff.toml
cloudcoil/codegen/_tomllib/__init__.py
cloudcoil/codegen/_tomllib/_parser.py
cloudcoil/codegen/_tomllib/_re.py
cloudcoil/codegen/_tomllib/_types.py
cloudcoil/codegen/templates/pydantic_v2/BaseModel.jinja2
cloudcoil/codegen/templates/pydantic_v2/RootModel.jinja2
cloudcoil-0.5.8.dist-info/METADATA
cloudcoil-0.5.8.dist-info/WHEEL
cloudcoil-0.5.8.dist-info/entry_points.txt
cloudcoil-0.5.8.dist-info/licenses/LICENSE
cloudcoil-0.5.8.dist-info/RECORD
