Metadata-Version: 2.4
Name: cloudcoil
Version: 0.5.8
Summary: Cloud native made easy with Python
Project-URL: Homepage, https://github.com/cloudcoil/cloudcoil
Project-URL: Documentation, https://cloudcoil.github.io/cloudcoil
Project-URL: Repository, https://github.com/cloudcoil/cloudcoil
Project-URL: Issues, https://github.com/cloudcoil/cloudcoil/issues
Project-URL: Changelog, https://github.com/cloudcoil/cloudcoil/releases
Author-email: Sambhav Kothari <sambhavs.email@gmail.com>
Maintainer-email: Sambhav Kothari <sambhavs.email@gmail.com>
License: Apache-2.0
License-File: LICENSE
Keywords: async,cloud-native,kubernetes,pydantic,python
Classifier: Programming Language :: Python :: 3.10
Classifier: Programming Language :: Python :: 3.11
Classifier: Programming Language :: Python :: 3.12
Classifier: Programming Language :: Python :: 3.13
Requires-Python: >=3.10
Requires-Dist: httpx
Requires-Dist: pydantic>2.0
Requires-Dist: pyyaml>=6.0.2
Requires-Dist: typing-extensions>=4.0.0; python_version <= '3.10'
Provides-Extra: all-models
Requires-Dist: cloudcoil-models-cert-manager; extra == 'all-models'
Requires-Dist: cloudcoil-models-fluxcd; extra == 'all-models'
Requires-Dist: cloudcoil-models-istio; extra == 'all-models'
Requires-Dist: cloudcoil-models-keda; extra == 'all-models'
Requires-Dist: cloudcoil-models-knative-eventing; extra == 'all-models'
Requires-Dist: cloudcoil-models-knative-serving; extra == 'all-models'
Requires-Dist: cloudcoil-models-kpack; extra == 'all-models'
Requires-Dist: cloudcoil-models-kubernetes; extra == 'all-models'
Requires-Dist: cloudcoil-models-kyverno; extra == 'all-models'
Requires-Dist: cloudcoil-models-prometheus-operator; extra == 'all-models'
Requires-Dist: cloudcoil-models-sealed-secrets; extra == 'all-models'
Requires-Dist: cloudcoil-models-velero; extra == 'all-models'
Provides-Extra: cert-manager
Requires-Dist: cloudcoil-models-cert-manager; extra == 'cert-manager'
Provides-Extra: codegen
Requires-Dist: datamodel-code-generator[http]~=0.26.4; extra == 'codegen'
Requires-Dist: ruff; extra == 'codegen'
Provides-Extra: fluxcd
Requires-Dist: cloudcoil-models-fluxcd; extra == 'fluxcd'
Provides-Extra: istio
Requires-Dist: cloudcoil-models-istio; extra == 'istio'
Provides-Extra: keda
Requires-Dist: cloudcoil-models-keda; extra == 'keda'
Provides-Extra: knative-eventing
Requires-Dist: cloudcoil-models-knative-eventing; extra == 'knative-eventing'
Provides-Extra: knative-serving
Requires-Dist: cloudcoil-models-knative-serving; extra == 'knative-serving'
Provides-Extra: kpack
Requires-Dist: cloudcoil-models-kpack; extra == 'kpack'
Provides-Extra: kubernetes
Requires-Dist: cloudcoil-models-kubernetes; extra == 'kubernetes'
Provides-Extra: kubernetes-1-29
Requires-Dist: cloudcoil-models-kubernetes~=1.29.0; extra == 'kubernetes-1-29'
Provides-Extra: kubernetes-1-30
Requires-Dist: cloudcoil-models-kubernetes~=1.30.0; extra == 'kubernetes-1-30'
Provides-Extra: kubernetes-1-31
Requires-Dist: cloudcoil-models-kubernetes~=1.31.0; extra == 'kubernetes-1-31'
Provides-Extra: kubernetes-1-32
Requires-Dist: cloudcoil-models-kubernetes~=1.32.0; extra == 'kubernetes-1-32'
Provides-Extra: kyverno
Requires-Dist: cloudcoil-models-kyverno; extra == 'kyverno'
Provides-Extra: prometheus-operator
Requires-Dist: cloudcoil-models-prometheus-operator; extra == 'prometheus-operator'
Provides-Extra: sealed-secrets
Requires-Dist: cloudcoil-models-sealed-secrets; extra == 'sealed-secrets'
Provides-Extra: test
Requires-Dist: filelock; extra == 'test'
Requires-Dist: pytest; extra == 'test'
Requires-Dist: pytest-asyncio; extra == 'test'
Provides-Extra: truststore
Requires-Dist: truststore>=0.8.0; extra == 'truststore'
Provides-Extra: velero
Requires-Dist: cloudcoil-models-velero; extra == 'velero'
